[
  {
    "playlists": [],
    "topics": [],
    "public": true,
    "_id": "Hoa5bUEyp2Q",
    "__v": 0,
    "description": "Wahoo have released a new smart roller, the Rollr. It essentially allows you to link up your indoor rides to virtual worlds. Ollie takes you through everything you need to know about Wahoo's latest smart tech!\n\nIn association with @wahoofitness 👉 http://gcn.eu/Wahoo-Fitness \nClick here to enter the competition 👉 https://gcn.eu/WahooCompetition\n\nUseful Links\nAdventure Documentaries, Exclusive Shows & Live Racing on GCN+: https://gcn.eu/plus\nDownload the GCN App for free: https://gcn.eu/app\nVisit the GCN Shop: https://gcn.eu/NewArrivals\nJoin the GCN Club: https://www.gcnclub.com/\n\nWatch more on GCN Tech...\n📹  New Wahoo Powrlink Zero Pedals 👉 https://gcntech.co/zS\n📹  Watch our Editor’s Choice Playlist 👉  https://gcntech.co/EditorsChoice \n📹  Watch the latest GCN Tech Show 👉  https://gcntech.co/GCNTechShow \n\n🎵 Music - licensed by Epidemic Sound / Artlist 🎵 \nTimmy - AGST\nBryant Bark - Dylan Sitts\nLocked On - A P O L L O\nYour Hands on Me (Instrumental Version) - NIGHTCAP\n\n#gcntech #gcn #cycling #roadbike \n\nPhotos: © Velo Collection (TDW) / Getty Images & © Bettiniphoto / http://www.bettiniphoto.net/\n\nBrought to you by the world’s biggest cycling channel, the Global Cycling Network (GCN), GCN Tech is the only channel you need for all things bike tech – past, present and future.\n\nSimply put, we’re obsessed with tech: we seek out and showcase the best in bikes, components, tech, accessories, upgrades and more from races and events, tech shows and product launches across the globe to bring you the best in road bike technology.\n\nWe’ve also got great maintenance videos to help you get the most from your bike; pro-bike tours from all the biggest races; special features and the weekly GCN Tech Show. We also take a deeper look into the future of cycling, apps, smart tech and virtual riding. \n\nJoin us on the channel and the GCN App to submit your content, vote on the latest tech and keep abreast of exciting new trends. \n\nThanks to our sponsors:\n\nCastelli Clothing: https://gcn.eu/Castelli\nGiro Helmets: https://gcn.eu/Giro\nPinarello Bikes: https://gcn.eu/Pinarello\nZipp Wheels: https://gcn.eu/Zipp\nEnervit Nutrition: https://gcn.eu/Enervit\nTopeak Tools: http://gcn.eu/Topeak\nCanyon Bikes: http://gcn.eu/-Canyon\nPirelli Tyres: https://gcn.eu/Pirelli\nOrbea Bikes: http://gcn.eu/Orbea\nVision Wheels: http://gcn.eu/Vision\nWahoo Fitness: http://gcn.eu/Wahoo-Fitness \nPark Tool: http://gcn.eu/-parktool\nElite Bottles: https://gcn.eu/EliteBottles\nWhoop Fitness: https://gcn.eu/Whoop\nKomoot: https://gcn.eu/komoot\nSelle Italia: https://gcn.eu/SelleItalia\nZwift: https://gcn.eu/Zwift\nShimano Wheels: https://gcn.eu/Shimano\nShadow Stand: https://gcn.eu/ShadowStand\nDMT Shoes: https://gcn.eu/DMT\nMuc-Off: https://gcn.eu/MucOff\n\nWatch our sister channels:\nGlobal Cycling Network - https://www.youtube.com/gcn \nGCN Racing - https://www.youtube.com/gcnracing \nGlobal Triathlon Network - https://www.youtube.com/gtn \nGCN Italia - https://www.youtube.com/gcnitalia \nGCN en Espanol - https://www.youtube.com/gcnenespanol \nGCN auf Deutsch - https://www.youtube.com/gcnaufdeutsch \nGCN en Francais - https://www.youtube.com/gcnenfrancais \nGCN Japan - https://www.youtube.com/gcnjapan \nGCN Training - https://www.youtube.com/gcntraining \nGlobal Mountain Bike Network - https://youtube.com/gmbn\nGMBN Tech - https://www.youtube.com/gmbntech \nElectric Mountain Bike Network - https://www.youtube.com/embn",
    "publishDate": "2022-02-25T18:30:59.000Z",
    "title": "Wahoo Rollr Smart Trainer Unboxing & Giveaway!!",
    "urlTitle": "wahoo-rollr-smart-trainer-unboxing-giveaway"
  },
  {
    "playlists": [],
    "topics": [],
    "public": true,
    "_id": "qhor-Urfu0g",
    "__v": 0,
    "description": "Conor gives you some top bikepacking tips, find a good spot, set up a tent, become a banana...\n\nUseful Links:\nAdventure Documentaries, Exclusive Shows & Live Racing on GCN+: https://gcn.eu/plus\nDownload the GCN App for free: https://gcn.eu/app\nJoin us at the Global Bike Festival: https://gcn.eu/global-bike-festival \nVisit the GCN Shop: https://gcn.eu/NewArrivals\nJoin the GCN Club: https://www.gcnclub.com/\n\nWatch more on GCN...\n📹  Watch our Editor’s Choice Playlist 👉  https://gcn.eu/editorschoice\n📹  Or why not check out our Features Playlist 👉 ​​ https://gcn.eu/gcnfeatures \n\n🎵 Music - licensed by Epidemic Sound / Artlist 🎵\n\n#gcn #cycling #roadbike #bikepacking #bikepack #adventurecycling #adventure \n\nPhotos: © Velo Collection (TDW) / Getty Images & © Bettiniphoto / http://www.bettiniphoto.net/\n\nThe Global Cycling Network (GCN) is the largest online cycling channel in the world, bringing together a global community of road cyclists to celebrate everything that’s great about the world of cycling.\n\nOur videos bring fans compelling daily content including expert tutorials, techniques, training, racing, cutting-edge bike tech, unparalleled behind the scenes event coverage, humour,  entertainment, and more.\n\nPresented by ex-pro riders, GCN offers a uniquely qualified insight into the world of cycling, and most importantly it’s fuelled by our passionate and enthusiastic fans – everyone who makes up the GCN community. We also bring the latest and greatest tech to your attention, showcase the best places in the world to ride and get exclusive access to events and races.\n\nWelcome to the Global Cycling Network | Inside Cycling\n\nThanks to our sponsors:\n\nCastelli Clothing: https://gcn.eu/Castelli\nGiro Helmets: https://gcn.eu/Giro\nPinarello Bikes: https://gcn.eu/Pinarello\nZipp Wheels: https://gcn.eu/Zipp\nEnervit Nutrition: https://gcn.eu/Enervit\nTopeak Tools: http://gcn.eu/Topeak\nCanyon Bikes: http://gcn.eu/-Canyon\nPirelli Tyres: https://gcn.eu/Pirelli\nOrbea Bikes: http://gcn.eu/Orbea\nVision Wheels: http://gcn.eu/Vision\nWahoo Fitness: http://gcn.eu/Wahoo-Fitness \nPark Tool: http://gcn.eu/-parktool\nElite Bottles: https://gcn.eu/EliteBottles\nWhoop Fitness: https://gcn.eu/Whoop\nKomoot: https://gcn.eu/komoot\nSelle Italia: https://gcn.eu/SelleItalia\nZwift: https://gcn.eu/Zwift\nShimano Wheels: https://gcn.eu/Shimano\nShadow Stand: https://gcn.eu/ShadowStand\nDMT Shoes: https://gcn.eu/DMT\nMuc-Off: https://gcn.eu/MucOff\n\nWatch our sister channels:\n@GCN Tech\n@GCN Racing\n@Global Triathlon Network \n@GCN Italia \n@GCN en Espanol\n@GCN auf Deutsch\n@GCN en Francais\n@GCN Japan\n@GCN Training\n@Global Mountain Bike Network\n@GMBN Tech\n@Electric Mountain Bike Network",
    "publishDate": "2022-02-25T14:00:21.000Z",
    "title": "I'm A Banana... #shorts",
    "urlTitle": "im-a-banana-shorts"
  },
  {
    "playlists": [],
    "topics": [],
    "public": true,
    "_id": "KwHPRk8rLpQ",
    "__v": 0,
    "description": "Sometimes the best way to vary up your riding and find new roads is to ditch the GPS, get rid of the map, follow your internal compass, and just get completely lost! Conor and Manon are in the Algarve, showing you their top tips on getting lost!\n____________________\n🚴 With the 2022 road season promising to be one of the most exciting in recent memory, subscribe to GCN+ for live racing all year round, exclusive shows & cycling adventure films: https://gcn.eu/plus\nDownload the GCN App 📲  for FREE & be part of the world's largest cycling community: https://gcn.eu/app\nJoin thousands of other cycling fans in receiving our free weekly ✉️ newsletter roundup, including news, competitions and discounts: https://gcn.eu/3K7\n\nVisit the GCN Shop - Shop Now: https://gcn.eu/NewArrivals\nSubscribe to GCN: http://gcn.eu/SubscribeToGCN\nRegister your interest in the GCN Club: https://www.gcnclub.com/\n#Cycling #GCN #RoadBike \n\nJoin us from 16-19 June 2022 in the stunning resort of Saalbach in the heart of the Austrian Alps for Global Bike Festival - the ultimate weekend of bikes, riding, music, entertainment and much, much more brought to you by GCN, GMBN and EMBN: https://gcn.eu/global-bike-festival\n\nHave you ever got lost on a bike ride? Let us know in the comments! 👇\n\nIf you enjoyed this video, make sure to give it a thumbs up and share it with your friends. 👍\n\nWatch more on GCN...\n📹  Corner Like A Cyclocross Pro 👉 https://gcn.eu/CyclocrossCornering\n\nMusic - licensed by Epidemic Sound:\nLibertalia - Arc De Soleil\nEncore in Polynesia\n\nPhotos: © Velo Collection (TDW) / Getty Images & © Bettiniphoto / http://www.bettiniphoto.net/\n\nThe Global Cycling Network (GCN) is the largest and fastest-growing online cycling channel in the world, bringing together a global community of road cyclists to celebrate everything that’s great about the world of cycling. \n\nOur videos bring fans compelling daily content including expert tutorials, techniques, training, racing, cutting-edge bike tech, unparalleled behind the scenes event coverage, humour,  entertainment, and more. \n\nPresented by ex-pro riders, GCN offers a uniquely qualified insight into the world of cycling, and most importantly it’s fuelled by our passionate and enthusiastic fans – everyone who makes up the GCN community. We also bring you the latest and greatest tech to your attention, showcase the best places in the world to ride and get exclusive access to events and races. \n\nWelcome to the Global Cycling Network | Inside #cycling\n\nThanks to our sponsors:\n\nCastelli Clothing: https://gcn.eu/Castelli\nGiro Helmets: https://gcn.eu/Giro\nPinarello Bikes: https://gcn.eu/Pinarello\nZipp Wheels: https://gcn.eu/Zipp\nEnervit Nutrition: https://gcn.eu/Enervit\nTopeak Tools: http://gcn.eu/Topeak\nCanyon Bikes: http://gcn.eu/-Canyon\nPirelli Tyres: https://gcn.eu/Pirelli\nOrbea Bikes: http://gcn.eu/Orbea\nVision Wheels: http://gcn.eu/Vision\nWahoo Fitness: http://gcn.eu/Wahoo-Fitness \nPark Tool: http://gcn.eu/-parktool\nElite Bottles: https://gcn.eu/EliteBottles\nWhoop Fitness: https://gcn.eu/Whoop\nKomoot: https://gcn.eu/komoot\nSelle Italia: https://gcn.eu/SelleItalia\nZwift: https://gcn.eu/Zwift\nShimano Wheels: https://gcn.eu/Shimano\nShadow Stand: https://gcn.eu/ShadowStand\nDMT Shoes: https://gcn.eu/DMT\nMuc-Off: https://gcn.eu/MucOff\n\nFacebook: http://gcn.eu/gcnFb\nInstagram: http://gcn.eu/GCNInsta\nTwitter: http://gcn.eu/gcnTW\nYouTube Channel: http://gcn.eu/gcnYT\nThe GCN Club: http://gcn.eu/club\n\nGCN Japan: https://gcn.eu/subscribe-gcn-japan\nGCN Italia: https://gcn.eu/GCN-Italia\nGCN en Español: http://gcn.eu/Suscribirse\nGCN auf Deutsch: https://gcn.eu/auf-deutsch\nGCN en Français: https://gcn.eu/GCNENFRANCAIS\nGCN Tech: http://gcntech.co/subscribe\nGCN Training: https://gcn.eu/gcntraining\nGCN Racing: https://gcn.eu/gcn-racing\nGMBN: http://gmbn.eu/subscribe\nGMBN Tech: http://gmbn.tech/subscribe\nEMBN: http://embn.me/subscribe\n\nLeave us a comment below!",
    "publishDate": "2022-02-25T10:00:21.000Z",
    "title": "How To Get Lost: Our Top Tips!",
    "urlTitle": "how-to-get-lost-our-top-tips"
  },
  {
    "playlists": [],
    "topics": [],
    "public": true,
    "_id": "tHlKWmnRSe8",
    "__v": 0,
    "description": "Cycling nutrition doesn't need to be expensive, so Manon has decided to share with you a few of her favourite budget snacks from The Cyclist's Cookbook to take on a bike ride. They are all super easy to make and really tasty too. Get the right fuel without needing to spend big!\n\nGet The Cyclist's Cookbook from the GCN Shop 👉 https://gcn.eu/6Lr\n\n0:00 Intro\n1:00 Rice Cakes (Part 1)\n2:46 PB&J Panini\n4:12 Gravel Mix\n5:54 Post Ride Beans & Tuna Pitta\n6:52 Rice Cakes (Part 2)\n\nUseful Links:\nAdventure Documentaries, Exclusive Shows & Live Racing on GCN+: https://gcn.eu/plus\nDownload the GCN App for free: https://gcn.eu/app\nJoin us at the Global Bike Festival: https://gcn.eu/global-bike-festival \nVisit the GCN Shop: https://gcn.eu/NewArrivals\nJoin the GCN Club: https://www.gcnclub.com/\n\nWhat snacks do you like to take on your rides? Let us know in the comments below! 💬\n\nIf you liked this video, be sure to give it a thumbs up 👍 and share it with your friends!\n\nWatch more on GCN...\n📹  Ride Fast: Top Tips For Cycling At High Speed 👉 https://gcn.eu/6-k\n📹  Watch our Editor’s Choice Playlist 👉  https://gcn.eu/editorschoice\n📹  Or why not check out our Features Playlist 👉 ​​ https://gcn.eu/gcnfeatures \n\n🎵 Music - licensed by Epidemic Sound 🎵 \nMeander - Jobii\nLet You Go (Daxten Remix)\nBryant Bark - Dylan Sitts\nThe Ace - Ballpoint\n\n#gcn #cycling #roadbike #gcntraining #cyclistscookbook #cyclingnutrition #sportsnutrition\n\nPhotos: © Velo Collection (TDW) / Getty Images & © Bettiniphoto / http://www.bettiniphoto.net/\n\nThe Global Cycling Network (GCN) is the largest online cycling channel in the world, bringing together a global community of road cyclists to celebrate everything that’s great about the world of cycling.\n\nOur videos bring fans compelling daily content including expert tutorials, techniques, training, racing, cutting-edge bike tech, unparalleled behind the scenes event coverage, humour,  entertainment, and more.\n\nPresented by ex-pro riders, GCN offers a uniquely qualified insight into the world of cycling, and most importantly it’s fuelled by our passionate and enthusiastic fans – everyone who makes up the GCN community. We also bring the latest and greatest tech to your attention, showcase the best places in the world to ride and get exclusive access to events and races.\n\nWelcome to the Global Cycling Network | Inside Cycling\n\nThanks to our sponsors:\n\nCastelli Clothing: https://gcn.eu/Castelli\nGiro Helmets: https://gcn.eu/Giro\nPinarello Bikes: https://gcn.eu/Pinarello\nZipp Wheels: https://gcn.eu/Zipp\nEnervit Nutrition: https://gcn.eu/Enervit\nTopeak Tools: http://gcn.eu/Topeak\nCanyon Bikes: http://gcn.eu/-Canyon\nPirelli Tyres: https://gcn.eu/Pirelli\nOrbea Bikes: http://gcn.eu/Orbea\nVision Wheels: http://gcn.eu/Vision\nWahoo Fitness: http://gcn.eu/Wahoo-Fitness \nPark Tool: http://gcn.eu/-parktool\nElite Bottles: https://gcn.eu/EliteBottles\nWhoop Fitness: https://gcn.eu/Whoop\nKomoot: https://gcn.eu/komoot\nSelle Italia: https://gcn.eu/SelleItalia\nZwift: https://gcn.eu/Zwift\nShimano Wheels: https://gcn.eu/Shimano\nShadow Stand: https://gcn.eu/ShadowStand\nDMT Shoes: https://gcn.eu/DMT\nMuc-Off: https://gcn.eu/MucOff\n\nWatch our sister channels:\nWatch our sister channels:\nGCN Tech - https://www.youtube.com/gcntech \nGCN Racing - https://www.youtube.com/gcnracing \nGlobal Triathlon Network - https://www.youtube.com/gtn \nGCN Italia - https://www.youtube.com/gcnitalia \nGCN en Espanol - https://www.youtube.com/gcnenespanol \nGCN auf Deutsch - https://www.youtube.com/gcnaufdeutsch \nGCN en Francais - https://www.youtube.com/gcnenfrancais \nGCN Japan - https://www.youtube.com/gcnjapan \nGCN Training - https://www.youtube.com/gcntraining \nGlobal Mountain Bike Network - https://youtube.com/gmbn\nGMBN Tech - https://www.youtube.com/gmbntech \nElectric Mountain Bike Network - https://www.youtube.com/embn",
    "publishDate": "2022-02-24T18:43:39.000Z",
    "title": "Cheap & Easy Snacks To Make For Your Bike Rides",
    "urlTitle": "cheap-easy-snacks-to-make-for-your-bike-rides"
  },
  {
    "playlists": [],
    "topics": [],
    "public": true,
    "_id": "hAXXbNNpYMc",
    "__v": 0,
    "description": "On this week’s GCN Tech Show, Alex and Ollie look into the true cost of bike ownership. How much does it cost per day or per ride when all elements of owning a bike are considered? It may make a superbike seem cheaper than you’d think! We’ve also got more hot tech, the best bike shop in the world (*this week) and your bike vault submissions.\n\n00:00 Intro\n00:30 Last Week’s Poll\n01:27 True Cost of Bike Ownership\n07:33 This Week’s Poll\n08:20 Hot Tech\n15:34 Best Bike Shop in the World (*This Week)\n18:25 Bike Vault\n\nUseful Links\nAdventure Documentaries, Exclusive Shows & Live Racing on GCN+: https://gcn.eu/plus\nDownload the GCN App for free: https://gcn.eu/app\nVisit the GCN Shop: https://gcn.eu/NewArrivals\nJoin the GCN Club: https://www.gcnclub.com/\n\nHow much would you pay per ride to own the bike of your dreams? Let us know in the comments below! 💬\n\nThis Week’s Poll:\nWould you buy a $6,000 bike if you could own it for $20 per week spread over 5 years? 👉 https://gcntech.co/zQ\n\nThe Best Bike Shop in the World (*This Week):\nOliver’s Bicycle Workshop 👉 https://gcntech.co/zK\n\nBike Vault:\nCannondale SystemSix Hi-MOD 👉 https://gcntech.co/zR\nTrek Madone SL7 👉 https://gcntech.co/zL\nSpecialized S-Works Tarmac SL5 👉 https://gcntech.co/zM\nSpecialized S-Works Venge ViAS 👉 https://gcntech.co/zN\nCannondale SystemSix 👉 https://gcntech.co/zO\nAllied Able 👉 https://gcntech.co/zP\n\nEnter your own bike and vote on other Bike Vault submissions on the GCN App! 📲 \n\nIf you liked this video, be sure to give it a thumbs up 👍 and share it with your friends!\n\nWatch more on GCN Tech...\n📹  How Much Slower Does A Cheap Bike Climb? 👉 https://gcntech.co/EurobikeClimb\n📹  Watch our Editor’s Choice Playlist 👉  https://gcntech.co/EditorsChoice \n📹  Watch the latest GCN Tech Show 👉  https://gcntech.co/GCNTechShow \n\n🎵 Music - licensed by Epidemic Sound 🎵\nMy Wildfire - Felix Johansson Carne\nGamma Ray Sky - La Boucle\nWe've Got a Good Thing Going - Matt Large\nSunrise - Shiruky\n\n#gcntech #gcn #cycling #roadbike #gcntechshow #techshow #biketech #hottech #bikevault\n\nPhotos: © Velo Collection (TDW) / Getty Images & © Bettiniphoto / http://www.bettiniphoto.net/\n\nBrought to you by the world’s biggest cycling channel, the Global Cycling Network (GCN), GCN Tech is the only channel you need for all things bike tech – past, present and future.\n\nSimply put, we’re obsessed with tech: we seek out and showcase the best in bikes, components, tech, accessories, upgrades and more from races and events, tech shows and product launches across the globe to bring you the best in road bike technology.\n\nWe’ve also got great maintenance videos to help you get the most from your bike; pro-bike tours from all the biggest races; special features and the weekly GCN Tech Show. We also take a deeper look into the future of cycling, apps, smart tech and virtual riding. \n\nJoin us on the channel and the GCN App to submit your content, vote on the latest tech and keep abreast of exciting new trends. \n\nThanks to our sponsors:\n\nCastelli Clothing: https://gcn.eu/Castelli\nGiro Helmets: https://gcn.eu/Giro\nPinarello Bikes: https://gcn.eu/Pinarello\nZipp Wheels: https://gcn.eu/Zipp\nEnervit Nutrition: https://gcn.eu/Enervit\nTopeak Tools: http://gcn.eu/Topeak\nCanyon Bikes: http://gcn.eu/-Canyon\nPirelli Tyres: https://gcn.eu/Pirelli\nOrbea Bikes: http://gcn.eu/Orbea\nVision Wheels: http://gcn.eu/Vision\nWahoo Fitness: http://gcn.eu/Wahoo-Fitness \nPark Tool: http://gcn.eu/-parktool\nElite Bottles: https://gcn.eu/EliteBottles\nWhoop Fitness: https://gcn.eu/Whoop\nKomoot: https://gcn.eu/komoot\nSelle Italia: https://gcn.eu/SelleItalia\nZwift: https://gcn.eu/Zwift\nShimano Wheels: https://gcn.eu/Shimano\nShadow Stand: https://gcn.eu/ShadowStand\nDMT Shoes: https://gcn.eu/DMT\nMuc-Off: https://gcn.eu/MucOff\n\nWatch our sister channels:\nGlobal Cycling Network - https://www.youtube.com/gcn \nGCN Racing - https://www.youtube.com/gcnracing \nGlobal Triathlon Network - https://www.youtube.com/gtn \nGCN Italia - https://www.youtube.com/gcnitalia \nGCN en Espanol - https://www.youtube.com/gcnenespanol \nGCN auf Deutsch - https://www.youtube.com/gcnaufdeutsch \nGCN en Francais - https://www.youtube.com/gcnenfrancais \nGCN Japan - https://www.youtube.com/gcnjapan \nGCN Training - https://www.youtube.com/gcntraining \nGlobal Mountain Bike Network - https://youtube.com/gmbn\nGMBN Tech - https://www.youtube.com/gmbntech \nElectric Mountain Bike Network - https://www.youtube.com/embn",
    "publishDate": "2022-02-24T15:31:20.000Z",
    "title": "What Is The True Cost Of Owning A Bike? | GCN Tech Show Ep. 218",
    "urlTitle": "what-is-the-true-cost-of-owning-a-bike-gcn-tech-show-ep-218"
  },
  {
    "playlists": [],
    "topics": [],
    "public": true,
    "_id": "F8cGGzyb9tQ",
    "__v": 0,
    "description": "For many of us, climbing is not all that fun. It's slow, hard and can get very sweaty. But it doesn't have to be this way! Manon shows you how you can make climbing easy-peasy, and unleash the mountain goat that's trapped inside you!\n\nTime Stamps: \n0:00 - Intro \n0:31 - Hold On! \n1:18 - Use Your Momentum \n2:08 - Use Hairpins \n2:36 - Shelter\n3:22 - Ride Our Of The Saddle\n\nUseful Links:\nAdventure Documentaries, Exclusive Shows & Live Racing on GCN+: https://gcn.eu/plus\nDownload the GCN App for free: https://gcn.eu/app\nJoin us at the Global Bike Festival: https://gcn.eu/global-bike-festival \nVisit the GCN Shop: https://gcn.eu/NewArrivals\nJoin the GCN Club: https://www.gcnclub.com/\n\nWhat do you find hardest about climbing? Let us know in the comments below!👇\n\nWatch more on GCN...\n📹  Climbing Mistakes To Avoid! 👉 https://gcn.eu/711\n📹  Watch our Editor’s Choice Playlist 👉  https://gcn.eu/editorschoice\n📹  Or why not check out our Features Playlist 👉​https://gcn.eu/gcnfeatures \n\n🎵 Music - licensed by Epidemic Sound / Artlist 🎵 \nHemisphere - Ooyy\n\n#gcn #cycling #roadbike #GCNHowTo #HowTo #Climbing \n\nPhotos: © Velo Collection (TDW) / Getty Images & © Bettiniphoto / http://www.bettiniphoto.net/\n\nThe Global Cycling Network (GCN) is the largest online cycling channel in the world, bringing together a global community of road cyclists to celebrate everything that’s great about the world of cycling.\n\nOur videos bring fans compelling daily content including expert tutorials, techniques, training, racing, cutting-edge bike tech, unparalleled behind the scenes event coverage, humour,  entertainment, and more.\n\nPresented by ex-pro riders, GCN offers a uniquely qualified insight into the world of cycling, and most importantly it’s fuelled by our passionate and enthusiastic fans – everyone who makes up the GCN community. We also bring the latest and greatest tech to your attention, showcase the best places in the world to ride and get exclusive access to events and races.\n\nWelcome to the Global Cycling Network | Inside Cycling\n\nThanks to our sponsors:\n\nCastelli Clothing: https://gcn.eu/Castelli\nGiro Helmets: https://gcn.eu/Giro\nPinarello Bikes: https://gcn.eu/Pinarello\nZipp Wheels: https://gcn.eu/Zipp\nEnervit Nutrition: https://gcn.eu/Enervit\nTopeak Tools: http://gcn.eu/Topeak\nCanyon Bikes: http://gcn.eu/-Canyon\nPirelli Tyres: https://gcn.eu/Pirelli\nOrbea Bikes: http://gcn.eu/Orbea\nVision Wheels: http://gcn.eu/Vision\nWahoo Fitness: http://gcn.eu/Wahoo-Fitness \nPark Tool: http://gcn.eu/-parktool\nElite Bottles: https://gcn.eu/EliteBottles\nWhoop Fitness: https://gcn.eu/Whoop\nKomoot: https://gcn.eu/komoot\nSelle Italia: https://gcn.eu/SelleItalia\nZwift: https://gcn.eu/Zwift\nShimano Wheels: https://gcn.eu/Shimano\nShadow Stand: https://gcn.eu/ShadowStand\nDMT Shoes: https://gcn.eu/DMT\nMuc-Off: https://gcn.eu/MucOff\n\nWatch our sister channels:\nWatch our sister channels:\nGCN Tech - https://www.youtube.com/gcntech \nGCN Racing - https://www.youtube.com/gcnracing \nGlobal Triathlon Network - https://www.youtube.com/gtn \nGCN Italia - https://www.youtube.com/gcnitalia \nGCN en Espanol - https://www.youtube.com/gcnenespanol \nGCN auf Deutsch - https://www.youtube.com/gcnaufdeutsch \nGCN en Francais - https://www.youtube.com/gcnenfrancais \nGCN Japan - https://www.youtube.com/gcnjapan \nGCN Training - https://www.youtube.com/gcntraining \nGlobal Mountain Bike Network - https://youtube.com/gmbn\nGMBN Tech - https://www.youtube.com/gmbntech \nElectric Mountain Bike Network - https://www.youtube.com/embn",
    "publishDate": "2022-02-23T17:58:37.000Z",
    "title": "How To Make Climbing Easier",
    "urlTitle": "how-to-make-climbing-easier"
  },
  {
    "playlists": [],
    "topics": [],
    "public": true,
    "_id": "iT4vxitB5_c",
    "__v": 0,
    "description": "Is a bike fit for a gravel bike the same as a road bike? Disc wheel or deep section wheel for a hilly ironman? Do I need to change my cassette to match my turbo trainer? Alex answers these questions and more on this week's Tech Clinic! \n\nChapters: \n0:00 - Intro \n0:19 - What's better for fitness, structured workouts or racing?\n1:27 - Can I leave a smart trainer outside in freezing weather? \n2:45 - In a bike fit is a gravel bike the same as a road bike?\n4:08 - What's the maximum width tyre for an old bike frame?\n5:42 - Do I need to change my cassette to match my turbo trainer?\n6:33 - Should a car roof rack grip a bike by the forks or the frame of a bike?\n7:56 - What do you cover the disc brake pads with when painting a bike?\n9:04 - Disc wheel or deep section wheel for a hilly ironman?\n\nUseful Links\nAdventure Documentaries, Exclusive Shows & Live Racing on GCN+: https://gcn.eu/plus\nDownload the GCN App for free: https://gcn.eu/app\nVisit the GCN Shop: https://gcn.eu/NewArrivals\nJoin the GCN Club: https://www.gcnclub.com/\n\nHave a tech question that needs answering? Use #AskGCNTech followed by your question in the comments below, and we'll get back to you in a future video!👇\n\nWatch more on GCN Tech...\n📹  New Wahoo Powrlink Zero Pedals 👉 https://gcn.eu/70-\n📹  Watch our Editor’s Choice Playlist 👉 https://gcntech.co/EditorsChoice \n📹  Watch the latest GCN Tech Show 👉 https://gcntech.co/GCNTechShow \n\n🎵 Music - licensed by Epidemic Sound / Artlist 🎵\nWe've Got a Good Thing Going - Matt Large\nNot Leaving without You - Matt Large\nA Smoke and a Pancake - Matt Large\n\n#gcntech #gcn #cycling #roadbike #TechClinic #AskGCN #AskGCNTech \n\nPhotos: © Velo Collection (TDW) / Getty Images & © Bettiniphoto / http://www.bettiniphoto.net/\n\nBrought to you by the world’s biggest cycling channel, the Global Cycling Network (GCN), GCN Tech is the only channel you need for all things bike tech – past, present and future.\n\nSimply put, we’re obsessed with tech: we seek out and showcase the best in bikes, components, tech, accessories, upgrades and more from races and events, tech shows and product launches across the globe to bring you the best in road bike technology.\n\nWe’ve also got great maintenance videos to help you get the most from your bike; pro-bike tours from all the biggest races; special features and the weekly GCN Tech Show. We also take a deeper look into the future of cycling, apps, smart tech and virtual riding. \n\nJoin us on the channel and the GCN App to submit your content, vote on the latest tech and keep abreast of exciting new trends. \n\nThanks to our sponsors:\n\nCastelli Clothing: https://gcn.eu/Castelli\nGiro Helmets: https://gcn.eu/Giro\nPinarello Bikes: https://gcn.eu/Pinarello\nZipp Wheels: https://gcn.eu/Zipp\nEnervit Nutrition: https://gcn.eu/Enervit\nTopeak Tools: http://gcn.eu/Topeak\nCanyon Bikes: http://gcn.eu/-Canyon\nPirelli Tyres: https://gcn.eu/Pirelli\nOrbea Bikes: http://gcn.eu/Orbea\nVision Wheels: http://gcn.eu/Vision\nWahoo Fitness: http://gcn.eu/Wahoo-Fitness \nPark Tool: http://gcn.eu/-parktool\nElite Bottles: https://gcn.eu/EliteBottles\nWhoop Fitness: https://gcn.eu/Whoop\nKomoot: https://gcn.eu/komoot\nSelle Italia: https://gcn.eu/SelleItalia\nZwift: https://gcn.eu/Zwift\nShimano Wheels: https://gcn.eu/Shimano\nShadow Stand: https://gcn.eu/ShadowStand\nDMT Shoes: https://gcn.eu/DMT\nMuc-Off: https://gcn.eu/MucOff\n\nWatch our sister channels:\nGlobal Cycling Network - https://www.youtube.com/gcn \nGCN Racing - https://www.youtube.com/gcnracing \nGlobal Triathlon Network - https://www.youtube.com/gtn \nGCN Italia - https://www.youtube.com/gcnitalia \nGCN en Espanol - https://www.youtube.com/gcnenespanol \nGCN auf Deutsch - https://www.youtube.com/gcnaufdeutsch \nGCN en Francais - https://www.youtube.com/gcnenfrancais \nGCN Japan - https://www.youtube.com/gcnjapan \nGCN Training - https://www.youtube.com/gcntraining \nGlobal Mountain Bike Network - https://youtube.com/gmbn\nGMBN Tech - https://www.youtube.com/gmbntech \nElectric Mountain Bike Network - https://www.youtube.com/embn",
    "publishDate": "2022-02-23T16:49:55.000Z",
    "title": "Can I Keep A Turbo Trainer In Freezing Weather? | Tech Clinic #AskGCNTech",
    "urlTitle": "can-i-keep-a-turbo-trainer-in-freezing-weather-tech-clinic-askgcntech"
  },
  {
    "playlists": [],
    "topics": [],
    "public": true,
    "_id": "oKJ9Xis_ZIY",
    "__v": 0,
    "description": "Ever wondered how an ultrasonic chain cleaner works? Alex finds out!\n\nCheck out @GCNTech for more content like this!\n____________________\n🚴 With the 2022 road season promising to be one of the most exciting in recent memory, subscribe to GCN+ for live racing all year round, exclusive shows & cycling adventure films: https://gcn.eu/plus\nDownload the GCN App 📲  for FREE & be part of the world's largest cycling community: https://gcn.eu/app\nJoin thousands of other cycling fans in receiving our free weekly ✉️ newsletter roundup, including news, competitions and discounts: https://gcn.eu/3K7\n\nJoin us from 16-19 June 2022 in the stunning resort of Saalbach in the heart of the Austrian Alps for Global Bike Festival - the ultimate weekend of bikes, riding, music, entertainment and much, much more brought to you by GCN, GMBN and EMBN: https://gcn.eu/global-bike-festival\n\nVisit the GCN Shop - Shop Now: https://gcn.eu/NewArrivals\nSubscribe to GCN: http://gcn.eu/SubscribeToGCN\nRegister your interest in the GCN Club: https://www.gcnclub.com/\n#Cycling #GCN #RoadBike \n\nIf you enjoyed this video, make sure to give it a thumbs up and share it with your friends. 👍\n\nMusic - licensed by Epidemic Sound\n\nPhotos: © Velo Collection (TDW) / Getty Images & © Bettiniphoto / http://www.bettiniphoto.net/\n\nThe Global Cycling Network (GCN) is the largest and fastest-growing online cycling channel in the world, bringing together a global community of road cyclists to celebrate everything that’s great about the world of cycling. \n\nOur videos bring fans compelling daily content including expert tutorials, techniques, training, racing, cutting-edge bike tech, unparalleled behind the scenes event coverage, humour,  entertainment, and more. \n\nPresented by ex-pro riders, GCN offers a uniquely qualified insight into the world of cycling, and most importantly it’s fuelled by our passionate and enthusiastic fans – everyone who makes up the GCN community. We also bring you the latest and greatest tech to your attention, showcase the best places in the world to ride and get exclusive access to events and races. \n\nWelcome to the Global Cycling Network | Inside #cycling\n\nThanks to our sponsors:\n\nCastelli Clothing: https://gcn.eu/Castelli\nGiro Helmets: https://gcn.eu/Giro\nPinarello Bikes: https://gcn.eu/Pinarello\nZipp Wheels: https://gcn.eu/Zipp\nEnervit Nutrition: https://gcn.eu/Enervit\nTopeak Tools: http://gcn.eu/Topeak\nCanyon Bikes: http://gcn.eu/-Canyon\nPirelli Tyres: https://gcn.eu/Pirelli\nOrbea Bikes: http://gcn.eu/Orbea\nVision Wheels: http://gcn.eu/Vision\nWahoo Fitness: http://gcn.eu/Wahoo-Fitness \nPark Tool: http://gcn.eu/-parktool\nElite Bottles: https://gcn.eu/EliteBottles\nWhoop Fitness: https://gcn.eu/Whoop\nKomoot: https://gcn.eu/komoot\nSelle Italia: https://gcn.eu/SelleItalia\nZwift: https://gcn.eu/Zwift\nShimano Wheels: https://gcn.eu/Shimano\nShadow Stand: https://gcn.eu/ShadowStand\nDMT Shoes: https://gcn.eu/DMT\nMuc-Off: https://gcn.eu/MucOff\n\nFacebook: http://gcn.eu/gcnFb\nInstagram: http://gcn.eu/GCNInsta\nTwitter: http://gcn.eu/gcnTW\nYouTube Channel: http://gcn.eu/gcnYT\nThe GCN Club: http://gcn.eu/club\n\nGCN Japan: https://gcn.eu/subscribe-gcn-japan\nGCN Italia: https://gcn.eu/GCN-Italia\nGCN en Español: http://gcn.eu/Suscribirse\nGCN auf Deutsch: https://gcn.eu/auf-deutsch\nGCN en Français: https://gcn.eu/GCNENFRANCAIS\nGCN Tech: http://gcntech.co/subscribe\nGCN Training: https://gcn.eu/gcntraining\nGCN Racing: https://gcn.eu/gcn-racing\nGMBN: http://gmbn.eu/subscribe\nGMBN Tech: http://gmbn.tech/subscribe\nEMBN: http://embn.me/subscribe\n\nLeave us a comment below!",
    "publishDate": "2022-02-23T14:00:24.000Z",
    "title": "How Do Ultrasonic Cleaners Work? #shorts",
    "urlTitle": "how-do-ultrasonic-cleaners-work-shorts"
  },
  {
    "playlists": [],
    "topics": [],
    "public": true,
    "_id": "hk60pCifFtM",
    "__v": 0,
    "description": "A few weeks ago, Conor told us about a CEO of a cargo bike courier company who has banned his employees from wearing helmets. It’s a controversial take but he claims cycling helmets increase risk when on the bike, so we caught up with him to find out his reasoning. We discuss this and more on this week’s GCN Show!\n\n00:00 Intro\n01:47 Bike Helmet Ban\n03:22 Interview with Ben from Pedal Me\n11:21 Helmet Ban Debate\n13:29 GCN Inspiration\n16:27 Cycling Shorts\n19:50 Coming Up on GCN+\n22:03 Hack/Bodge\n26:28 Caption Competition\n27:52 Comment of the Week\n31:00 Coming Up on YouTube\n\nUseful Links:\nAdventure Documentaries, Exclusive Shows & Live Racing on GCN+: https://gcn.eu/plus\nDownload the GCN App for free: https://gcn.eu/app\nJoin us at the Global Bike Festival: https://gcn.eu/global-bike-festival \nVisit the GCN Shop: https://gcn.eu/NewArrivals\nJoin the GCN Club: https://www.gcnclub.com/\n\nWhere do you stand on the helmet debate? Let us know in the comments below! 💬\n\nGCN Inspiration:\n1st place 👉 https://gcn.eu/70g\n2nd place 👉 https://gcn.eu/70h\n3rd place 👉 https://gcn.eu/70i\n\nHack/Bodge:\nBroadside Hack? 👉 https://gcn.eu/70j\nDeep Dish Aero Wheels 👉 https://gcn.eu/70k\nSpotted in Bogotá, Colombia 👉 https://gcn.eu/70l\nHandlebar with Integrated HR Sensor 👉 https://gcn.eu/70m\nRepair Cut on New Tyre 👉 https://gcn.eu/70n\n\nVote on next week’s hacks/bodges:\nIt’s Better Than Using My Flat Pedals 👉 https://gcn.eu/70o\nImpromptu Cable Routing Kit 👉 https://gcn.eu/70p\nPizza Box 👉 https://gcn.eu/70q\nMudguard Save 👉 https://gcn.eu/70r\nIndoor Use Only 👉 https://gcn.eu/70s\nBike Goes to Service 👉 https://gcn.eu/70t\nAllen Key Extension 👉 https://gcn.eu/70u\n\nSubmit your own hacks/bodges on the GCN App 📲\n\nWatch more on GCN...\n📹  Can We Ride The World's Longest Pro Bike Race Route? 👉 https://gcn.eu/RideSanremo \n📹  Watch our Editor’s Choice Playlist 👉  https://gcn.eu/editorschoice\n📹  Or why not check out our Features Playlist 👉 ​​ https://gcn.eu/gcnfeatures \n\n🎵 Music - licensed by Epidemic Sound / Artlist 🎵\nPower Drill Rev 3 - SFX Producer\nAfternoon Swing - Five Dime Fellas\nEqualX - Gregory David\nLilacs - [ocean jams]\nOlder Now - Rospigg_mk2\n\n#gcn #cycling #roadbike #gcnshow #gcninspiration #hackbodge #cyclingshorts #cyclingshow\n\nPhotos: © Velo Collection (TDW) / Getty Images & © Bettiniphoto / http://www.bettiniphoto.net/\n\nThe Global Cycling Network (GCN) is the largest online cycling channel in the world, bringing together a global community of road cyclists to celebrate everything that’s great about the world of cycling.\n\nOur videos bring fans compelling daily content including expert tutorials, techniques, training, racing, cutting-edge bike tech, unparalleled behind the scenes event coverage, humour,  entertainment, and more.\n\nPresented by ex-pro riders, GCN offers a uniquely qualified insight into the world of cycling, and most importantly it’s fuelled by our passionate and enthusiastic fans – everyone who makes up the GCN community. We also bring the latest and greatest tech to your attention, showcase the best places in the world to ride and get exclusive access to events and races.\n\nWelcome to the Global Cycling Network | Inside Cycling\n\nThanks to our sponsors:\n\nCastelli Clothing: https://gcn.eu/Castelli\nGiro Helmets: https://gcn.eu/Giro\nPinarello Bikes: https://gcn.eu/Pinarello\nZipp Wheels: https://gcn.eu/Zipp\nEnervit Nutrition: https://gcn.eu/Enervit\nTopeak Tools: http://gcn.eu/Topeak\nCanyon Bikes: http://gcn.eu/-Canyon\nPirelli Tyres: https://gcn.eu/Pirelli\nOrbea Bikes: http://gcn.eu/Orbea\nVision Wheels: http://gcn.eu/Vision\nWahoo Fitness: http://gcn.eu/Wahoo-Fitness \nPark Tool: http://gcn.eu/-parktool\nElite Bottles: https://gcn.eu/EliteBottles\nWhoop Fitness: https://gcn.eu/Whoop\nKomoot: https://gcn.eu/komoot\nSelle Italia: https://gcn.eu/SelleItalia\nZwift: https://gcn.eu/Zwift\nShimano Wheels: https://gcn.eu/Shimano\nShadow Stand: https://gcn.eu/ShadowStand\nDMT Shoes: https://gcn.eu/DMT\nMuc-Off: https://gcn.eu/MucOff\n\nWatch our sister channels:\n@GCN Tech\n@GCN Racing\n@Global Triathlon Network \n@GCN Italia \n@GCN en Espanol\n@GCN auf Deutsch\n@GCN en Francais\n@GCN Japan\n@GCN Training\n@Global Mountain Bike Network\n@GMBN Tech\n@Electric Mountain Bike Network",
    "publishDate": "2022-02-22T16:22:55.000Z",
    "title": "Ban Bike Helmets To Make Cycling Safer: Science Or Stupid? | GCN Show Ep. 476",
    "urlTitle": "ban-bike-helmets-to-make-cycling-safer-science-or-stupid-gcn-show-ep-476"
  },
  {
    "playlists": [],
    "topics": [],
    "public": true,
    "_id": "XY8y8rUohPM",
    "__v": 0,
    "description": "Power meters are a great tool for training, and in recent years have become a staple for all professional cyclists! Wahoo have been working on their latest powermeter, which is a pedal based system. Alex (finally!) shows you everything you need to know about them!\n\nIn association with @WahooFitness - https://gcn.eu/70w\n\n0:00 - Intro \n0:25 - What's inside the box? \n1:32 - Fitting the pedals\n3:07 - The benefit of pedal powermeters\n3:21 - Device compatibility\n5:02 - Charge and battery life\n5:57 - Performance test!\n6:41 - Stats and facts\n7:17 - Price \n7:32 - Wahoo App\n\nUseful Links\nAdventure Documentaries, Exclusive Shows & Live Racing on GCN+: https://gcn.eu/plus\nDownload the GCN App for free: https://gcn.eu/app\nVisit the GCN Shop: https://gcn.eu/NewArrivals\nJoin the GCN Club: https://www.gcnclub.com/\n\nWhat do you think of the new Wahoo Powrlink Zero Pedals? Let us know in the comments below! 👇\n\nWatch more on GCN Tech...\n📹  How To Set Up Wahoo Speedplay Cleats 👉 https://gcn.eu/6x7\n📹  Watch our Editor’s Choice Playlist 👉  https://gcntech.co/EditorsChoice \n📹  Watch the latest GCN Tech Show 👉 https://gcntech.co/GCNTechShow \n\n🎵 Music - licensed by Epidemic Sound / Artlist 🎵 \nWizzle - Guustavv\nThe Arcade - Lolife\nSomething about something - sarah, the illstrumentalist\nBag Mode - Dusty Decks\nFront Man - Heyson\nParticle Emission - Silver Maple\n\n#gcntech #gcn #cycling #roadbike #powermeter #firstlook #unboxing #wahoo #training\n\nPhotos: © Velo Collection (TDW) / Getty Images & © Bettiniphoto / http://www.bettiniphoto.net/\n\nBrought to you by the world’s biggest cycling channel, the Global Cycling Network (GCN), GCN Tech is the only channel you need for all things bike tech – past, present and future.\n\nSimply put, we’re obsessed with tech: we seek out and showcase the best in bikes, components, tech, accessories, upgrades and more from races and events, tech shows and product launches across the globe to bring you the best in road bike technology.\n\nWe’ve also got great maintenance videos to help you get the most from your bike; pro-bike tours from all the biggest races; special features and the weekly GCN Tech Show. We also take a deeper look into the future of cycling, apps, smart tech and virtual riding. \n\nJoin us on the channel and the GCN App to submit your content, vote on the latest tech and keep abreast of exciting new trends. \n\nThanks to our sponsors:\n\nCastelli Clothing: https://gcn.eu/Castelli\nGiro Helmets: https://gcn.eu/Giro\nPinarello Bikes: https://gcn.eu/Pinarello\nZipp Wheels: https://gcn.eu/Zipp\nEnervit Nutrition: https://gcn.eu/Enervit\nTopeak Tools: http://gcn.eu/Topeak\nCanyon Bikes: http://gcn.eu/-Canyon\nPirelli Tyres: https://gcn.eu/Pirelli\nOrbea Bikes: http://gcn.eu/Orbea\nVision Wheels: http://gcn.eu/Vision\nWahoo Fitness: http://gcn.eu/Wahoo-Fitness \nPark Tool: http://gcn.eu/-parktool\nElite Bottles: https://gcn.eu/EliteBottles\nWhoop Fitness: https://gcn.eu/Whoop\nKomoot: https://gcn.eu/komoot\nSelle Italia: https://gcn.eu/SelleItalia\nZwift: https://gcn.eu/Zwift\nShimano Wheels: https://gcn.eu/Shimano\nShadow Stand: https://gcn.eu/ShadowStand\nDMT Shoes: https://gcn.eu/DMT\nMuc-Off: https://gcn.eu/MucOff\n\nWatch our sister channels:\n@Global Cycling Network\n@GCN Racing\n@Global Triathlon Network \n@GCN Italia \n@GCN en Espanol\n@GCN auf Deutsch\n@GCN en Francais\n@GCN Japan\n@GCN Training\n@Global Mountain Bike Network\n@GMBN Tech\n@Electric Mountain Bike Network",
    "publishDate": "2022-02-22T14:41:51.000Z",
    "title": "New Wahoo Powrlink Zero Pedals | First Look!",
    "urlTitle": "new-wahoo-powrlink-zero-pedals-first-look"
  },
  {
    "playlists": [],
    "topics": [],
    "public": true,
    "_id": "3JDvoAxHvoo",
    "__v": 0,
    "description": "Bearings on a bicycle are often forgotten about, but having a smooth running bottom bracket really can make a world of difference! Alex shows you how to service and change your bearings.\n\nUseful Links\nAdventure Documentaries, Exclusive Shows & Live Racing on GCN+: https://gcn.eu/plus\nDownload the GCN App for free: https://gcn.eu/app\nVisit the GCN Shop: https://gcn.eu/NewArrivals\nJoin the GCN Club: https://www.gcnclub.com/\n\nHave you ever changed the bearings on your bike? Let us know in the comments below! \n\nWatch more on GCN Tech...\n📹  Hot Bike Tech At The 2022 UAE Tour! 👉 https://gcn.eu/70b\n📹  Watch our Editor’s Choice Playlist 👉 https://gcntech.co/EditorsChoice \n📹  Watch the latest GCN Tech Show 👉 https://gcntech.co/GCNTechShow \n\n🎵 Music - licensed by Epidemic Sound / Artlist 🎵 \nBig (Instrumental Version) - Pandaraps\nEnglish Breakfast - Jobii\n\n#gcntech #gcn #cycling #roadbike #maintenance #maintenancemonday #biketech #bikemaintenance #bearings\n\nPhotos: © Velo Collection (TDW) / Getty Images & © Bettiniphoto / http://www.bettiniphoto.net/\n\nBrought to you by the world’s biggest cycling channel, the Global Cycling Network (GCN), GCN Tech is the only channel you need for all things bike tech – past, present and future.\n\nSimply put, we’re obsessed with tech: we seek out and showcase the best in bikes, components, tech, accessories, upgrades and more from races and events, tech shows and product launches across the globe to bring you the best in road bike technology.\n\nWe’ve also got great maintenance videos to help you get the most from your bike; pro-bike tours from all the biggest races; special features and the weekly GCN Tech Show. We also take a deeper look into the future of cycling, apps, smart tech and virtual riding. \n\nJoin us on the channel and the GCN App to submit your content, vote on the latest tech and keep abreast of exciting new trends. \n\nThanks to our sponsors:\n\nCastelli Clothing: https://gcn.eu/Castelli\nGiro Helmets: https://gcn.eu/Giro\nPinarello Bikes: https://gcn.eu/Pinarello\nZipp Wheels: https://gcn.eu/Zipp\nEnervit Nutrition: https://gcn.eu/Enervit\nTopeak Tools: http://gcn.eu/Topeak\nCanyon Bikes: http://gcn.eu/-Canyon\nPirelli Tyres: https://gcn.eu/Pirelli\nOrbea Bikes: http://gcn.eu/Orbea\nVision Wheels: http://gcn.eu/Vision\nWahoo Fitness: http://gcn.eu/Wahoo-Fitness \nPark Tool: http://gcn.eu/-parktool\nElite Bottles: https://gcn.eu/EliteBottles\nWhoop Fitness: https://gcn.eu/Whoop\nKomoot: https://gcn.eu/komoot\nSelle Italia: https://gcn.eu/SelleItalia\nZwift: https://gcn.eu/Zwift\nShimano Wheels: https://gcn.eu/Shimano\nShadow Stand: https://gcn.eu/ShadowStand\nDMT Shoes: https://gcn.eu/DMT\nMuc-Off: https://gcn.eu/MucOff\n\nWatch our sister channels:\n@Global Cycling Network\n@GCN Racing\n@Global Triathlon Network \n@GCN Italia \n@GCN en Espanol\n@GCN auf Deutsch\n@GCN en Francais\n@GCN Japan\n@GCN Training\n@Global Mountain Bike Network\n@GMBN Tech\n@Electric Mountain Bike Network",
    "publishDate": "2022-02-21T16:21:02.000Z",
    "title": "How To Service Bearings On Your Bike",
    "urlTitle": "how-to-service-bearings-on-your-bike"
  },
  {
    "playlists": [],
    "topics": [],
    "public": true,
    "_id": "aj_D9FfYNGs",
    "__v": 0,
    "description": "What's the difference between a gravel bike and a cyclocross bike? We've teamed up with Trek Bikes to find out! \n\nIn association with @Trek Bicycle \n____________________\n🚴 With the 2022 road season promising to be one of the most exciting in recent memory, subscribe to GCN+ for live racing all year round, exclusive shows & cycling adventure films: https://gcn.eu/plus\nDownload the GCN App 📲  for FREE & be part of the world's largest cycling community: https://gcn.eu/app\nJoin thousands of other cycling fans in receiving our free weekly ✉️ newsletter roundup, including news, competitions and discounts: https://gcn.eu/3K7\n\nJoin us from 16-19 June 2022 in the stunning resort of Saalbach in the heart of the Austrian Alps for Global Bike Festival - the ultimate weekend of bikes, riding, music, entertainment and much, much more brought to you by GCN, GMBN and EMBN: https://gcn.eu/global-bike-festival\n\nVisit the GCN Shop - Shop Now: https://gcn.eu/NewArrivals\nSubscribe to GCN: http://gcn.eu/SubscribeToGCN\nRegister your interest in the GCN Club: https://www.gcnclub.com/\n#Cycling #GCN #RoadBike\n\nIf you enjoyed this video, make sure to give it a thumbs up and share it with your friends. 👍\n\nMusic - licensed by Epidemic Sound\n\nPhotos: © Velo Collection (TDW) / Getty Images & © Bettiniphoto / http://www.bettiniphoto.net/\n\nThe Global Cycling Network (GCN) is the largest and fastest-growing online cycling channel in the world, bringing together a global community of road cyclists to celebrate everything that’s great about the world of cycling. \n\nOur videos bring fans compelling daily content including expert tutorials, techniques, training, racing, cutting-edge bike tech, unparalleled behind the scenes event coverage, humour,  entertainment, and more. \n\nPresented by ex-pro riders, GCN offers a uniquely qualified insight into the world of cycling, and most importantly it’s fuelled by our passionate and enthusiastic fans – everyone who makes up the GCN community. We also bring you the latest and greatest tech to your attention, showcase the best places in the world to ride and get exclusive access to events and races. \n\nWelcome to the Global Cycling Network | Inside #cycling\n\nThanks to our sponsors:\n\nCastelli Clothing: https://gcn.eu/Castelli\nGiro Helmets: https://gcn.eu/Giro\nPinarello Bikes: https://gcn.eu/Pinarello\nZipp Wheels: https://gcn.eu/Zipp\nEnervit Nutrition: https://gcn.eu/Enervit\nTopeak Tools: http://gcn.eu/Topeak\nCanyon Bikes: http://gcn.eu/-Canyon\nPirelli Tyres: https://gcn.eu/Pirelli\nOrbea Bikes: http://gcn.eu/Orbea\nVision Wheels: http://gcn.eu/Vision\nWahoo Fitness: http://gcn.eu/Wahoo-Fitness \nPark Tool: http://gcn.eu/-parktool\nElite Bottles: https://gcn.eu/EliteBottles\nWhoop Fitness: https://gcn.eu/Whoop\nKomoot: https://gcn.eu/komoot\nSelle Italia: https://gcn.eu/SelleItalia\nZwift: https://gcn.eu/Zwift\nShimano Wheels: https://gcn.eu/Shimano\nShadow Stand: https://gcn.eu/ShadowStand\nDMT Shoes: https://gcn.eu/DMT\nMuc-Off: https://gcn.eu/MucOff\n\nFacebook: http://gcn.eu/gcnFb\nInstagram: http://gcn.eu/GCNInsta\nTwitter: http://gcn.eu/gcnTW\nYouTube Channel: http://gcn.eu/gcnYT\nThe GCN Club: http://gcn.eu/club\n\nGCN Japan: https://gcn.eu/subscribe-gcn-japan\nGCN Italia: https://gcn.eu/GCN-Italia\nGCN en Español: http://gcn.eu/Suscribirse\nGCN auf Deutsch: https://gcn.eu/auf-deutsch\nGCN en Français: https://gcn.eu/GCNENFRANCAIS\nGCN Tech: http://gcntech.co/subscribe\nGCN Training: https://gcn.eu/gcntraining\nGCN Racing: https://gcn.eu/gcn-racing\nGMBN: http://gmbn.eu/subscribe\nGMBN Tech: http://gmbn.tech/subscribe\nEMBN: http://embn.me/subscribe\n\nLeave us a comment below!",
    "publishDate": "2022-02-21T14:00:54.000Z",
    "title": "Gravel Vs Cyclocross Bike #shorts",
    "urlTitle": "gravel-vs-cyclocross-bike-shorts"
  },
  {
    "playlists": [],
    "topics": [],
    "public": true,
    "_id": "vAMCK9HdXgY",
    "__v": 0,
    "description": "Can Hank take on and beat a horse? Comment who you think won!\n____________________\n🚴 With the 2022 road season promising to be one of the most exciting in recent memory, subscribe to GCN+ for live racing all year round, exclusive shows & cycling adventure films: https://gcn.eu/plus\nDownload the GCN App 📲  for FREE & be part of the world's largest cycling community: https://gcn.eu/app\nJoin thousands of other cycling fans in receiving our free weekly ✉️ newsletter roundup, including news, competitions and discounts: https://gcn.eu/3K7\n\nJoin us from 16-19 June 2022 in the stunning resort of Saalbach in the heart of the Austrian Alps for Global Bike Festival - the ultimate weekend of bikes, riding, music, entertainment and much, much more brought to you by GCN, GMBN and EMBN: https://gcn.eu/global-bike-festival\n\nVisit the GCN Shop - Shop Now: https://gcn.eu/NewArrivals\nSubscribe to GCN: http://gcn.eu/SubscribeToGCN\nRegister your interest in the GCN Club: https://www.gcnclub.com/\n#Cycling #GCN #RoadBike \n\nIf you enjoyed this video, make sure to give it a thumbs up and share it with your friends. 👍\n\nMusic - licensed by Epidemic Sound\n\nPhotos: © Velo Collection (TDW) / Getty Images & © Bettiniphoto / http://www.bettiniphoto.net/\n\nThe Global Cycling Network (GCN) is the largest and fastest-growing online cycling channel in the world, bringing together a global community of road cyclists to celebrate everything that’s great about the world of cycling. \n\nOur videos bring fans compelling daily content including expert tutorials, techniques, training, racing, cutting-edge bike tech, unparalleled behind the scenes event coverage, humour,  entertainment, and more. \n\nPresented by ex-pro riders, GCN offers a uniquely qualified insight into the world of cycling, and most importantly it’s fuelled by our passionate and enthusiastic fans – everyone who makes up the GCN community. We also bring you the latest and greatest tech to your attention, showcase the best places in the world to ride and get exclusive access to events and races. \n\nWelcome to the Global Cycling Network | Inside #cycling\n\nThanks to our sponsors:\n\nCastelli Clothing: https://gcn.eu/Castelli\nGiro Helmets: https://gcn.eu/Giro\nPinarello Bikes: https://gcn.eu/Pinarello\nZipp Wheels: https://gcn.eu/Zipp\nEnervit Nutrition: https://gcn.eu/Enervit\nTopeak Tools: http://gcn.eu/Topeak\nCanyon Bikes: http://gcn.eu/-Canyon\nPirelli Tyres: https://gcn.eu/Pirelli\nOrbea Bikes: http://gcn.eu/Orbea\nVision Wheels: http://gcn.eu/Vision\nWahoo Fitness: http://gcn.eu/Wahoo-Fitness \nPark Tool: http://gcn.eu/-parktool\nElite Bottles: https://gcn.eu/EliteBottles\nWhoop Fitness: https://gcn.eu/Whoop\nKomoot: https://gcn.eu/komoot\nSelle Italia: https://gcn.eu/SelleItalia\nZwift: https://gcn.eu/Zwift\nShimano Wheels: https://gcn.eu/Shimano\nShadow Stand: https://gcn.eu/ShadowStand\nDMT Shoes: https://gcn.eu/DMT\nMuc-Off: https://gcn.eu/MucOff\n\nFacebook: http://gcn.eu/gcnFb\nInstagram: http://gcn.eu/GCNInsta\nTwitter: http://gcn.eu/gcnTW\nYouTube Channel: http://gcn.eu/gcnYT\nThe GCN Club: http://gcn.eu/club\n\nGCN Japan: https://gcn.eu/subscribe-gcn-japan\nGCN Italia: https://gcn.eu/GCN-Italia\nGCN en Español: http://gcn.eu/Suscribirse\nGCN auf Deutsch: https://gcn.eu/auf-deutsch\nGCN en Français: https://gcn.eu/GCNENFRANCAIS\nGCN Tech: http://gcntech.co/subscribe\nGCN Training: https://gcn.eu/gcntraining\nGCN Racing: https://gcn.eu/gcn-racing\nGMBN: http://gmbn.eu/subscribe\nGMBN Tech: http://gmbn.tech/subscribe\nEMBN: http://embn.me/subscribe\n\nLeave us a comment below!",
    "publishDate": "2022-02-20T14:00:51.000Z",
    "title": "CYCLIST VS HORSE #short",
    "urlTitle": "cyclist-vs-horse-short"
  },
  {
    "playlists": [],
    "topics": [],
    "public": true,
    "_id": "y57WQtgeHuM",
    "__v": 0,
    "description": "One of the first things cyclists look to upgrade on their bikes is usually tires and wheels, but just how much faster are fancy carbon aero wheels? Alex and Ollie are in Spain to put it to the test to find out just how much time can you save using expensive wheels and better tyres!\n____________________\n🚴 With the 2022 road season promising to be one of the most exciting in recent memory, subscribe to GCN+ for live racing all year round, exclusive shows & cycling adventure films: https://gcn.eu/plus\nDownload the GCN App 📲  for FREE & be part of the world's largest cycling community: https://gcn.eu/app\nJoin thousands of other cycling fans in receiving our free weekly ✉️ newsletter roundup, including news, competitions and discounts: https://gcn.eu/3K7\n\nJoin us from 16-19 June 2022 in the stunning resort of Saalbach in the heart of the Austrian Alps for Global Bike Festival - the ultimate weekend of bikes, riding, music, entertainment and much, much more brought to you by GCN, GMBN and EMBN: https://gcn.eu/global-bike-festival\n\nSubscribe: http://gcntech.co/subscribetogcntech\nThe GCN Shop: https://gcn.eu/NewArrivals\n#Cycling #GCN #GCNTech #RoadBike\n\nHave you noticed a big change from upgrading your tyres or wheels? Let us know in the comments below!👇\n\nIf you enjoyed this video, make sure to give it a thumbs up and share it with your friends. 👍\n\nWatch more on GCN Tech...\n📹 Should I Get A Frame That's A Little Big Or Small? 👉 https://gcn.eu/6-G\n\nMusic - licensed by Epidemic Sound:\nParadigm Shift - Gavin Luke\nYuma - Van Sandano\nGanja - Ooy\nTop Funnel - Ooy\nMagnum - Blue Steel\nRise Of the Velcro - Gabriel Lewis\nDreaming of Lhoste - Ooy\n\nPhotos: © Velo Collection (TDW) / Getty Images & © Bettiniphoto / http://www.bettiniphoto.net/\n\nBrought to you by the world’s biggest cycling channel, the Global Cycling Network (GCN), GCN Tech is the only channel you need for all things bike tech – past, present and future.\n\nSimply put, we’re obsessed with tech: we seek out and showcase the best in bikes, components, tech, accessories, upgrades and more from races and events, tech shows and product launches across the globe to bring you the best in road bike technology.\n\nWe’ve also got great maintenance videos to help you get the most from your bike; pro-bike tours from all the biggest races; special features and the weekly GCN Tech Show. We also take a deeper look into the future of cycling, apps, smart tech and virtual riding. \n\nJoin us on the channel and the GCN App to submit your content, vote on the latest tech and keep abreast of exciting new trends. \n\nThanks to our sponsors:\n\nCastelli Clothing: https://gcn.eu/Castelli\nGiro Helmets: https://gcn.eu/Giro\nPinarello Bikes: https://gcn.eu/Pinarello\nZipp Wheels: https://gcn.eu/Zipp\nEnervit Nutrition: https://gcn.eu/Enervit\nTopeak Tools: http://gcn.eu/Topeak\nCanyon Bikes: http://gcn.eu/-Canyon\nPirelli Tyres: https://gcn.eu/Pirelli\nOrbea Bikes: http://gcn.eu/Orbea\nVision Wheels: http://gcn.eu/Vision\nWahoo Fitness: http://gcn.eu/Wahoo-Fitness \nPark Tool: http://gcn.eu/-parktool\nElite Bottles: https://gcn.eu/EliteBottles\nWhoop Fitness: https://gcn.eu/Whoop\nKomoot: https://gcn.eu/komoot\nSelle Italia: https://gcn.eu/SelleItalia\nZwift: https://gcn.eu/Zwift\nShimano Wheels: https://gcn.eu/Shimano\nShadow Stand: https://gcn.eu/ShadowStand\nDMT Shoes: https://gcn.eu/DMT\nMuc-Off: https://gcn.eu/MucOff\n\nFacebook: http://gcntech.co/gcntechfb\nInstagram: http://gcntech.co/gcntechinsta\nTwitter: http://gcntech.co/gcntechtweet\nYouTube: http://gcntech.co/subscribe\n\nGCN: http://gcn.eu/SubscribeToGCN\nGCN Japan: https://gcn.eu/subscribe-gcn-japan\nGCN Italia: https://gcn.eu/GCN-Italia\nGCN en Español: http://gcn.eu/Suscribirse\nGCN auf Deutsch: https://gcn.eu/auf-deutsch\nGCN en Français: https://gcn.eu/GCNENFRANCAIS\nGCN Training: https://gcn.eu/gcntraining\nGCN Racing: https://gcn.eu/gcn-racing\nGMBN: http://gmbn.eu/subscribe\nGMBN Tech: http://gmbn.tech/subscribe\nEMBN: http://embn.me/subscribe\n\nLeave us a comment below!",
    "publishDate": "2022-02-20T10:00:33.000Z",
    "title": "Cheap Vs Expensive Wheels And Tyres | What's The Difference?",
    "urlTitle": "cheap-vs-expensive-wheels-and-tyres-whats-the-difference"
  },
  {
    "playlists": [],
    "topics": [],
    "public": true,
    "_id": "xoFnDmt0mLw",
    "__v": 0,
    "description": "Milan-San Remo is the world's longest bike race, a true epic at just under 300km! What happens if you try and ride it? With the help of our friends at Vitus Bikes, Ollie Bridgewood joins Alan Marangoni, a man who raced it five times in his career, to see just how hard it is to make it to Sanremo!\n\nIn association with Vitus Bikes 👉 https://gcn.eu/Vitus\nSubscribe to GCN+ 👉 https://gcn.eu/liveracing\n____________________\n🚴 With the 2022 road season promising to be one of the most exciting in recent memory, subscribe to GCN+ for live racing all year round, exclusive shows & cycling adventure films: https://gcn.eu/plus\nDownload the GCN App 📲  for FREE & be part of the world's largest cycling community: https://gcn.eu/app\nJoin thousands of other cycling fans in receiving our free weekly ✉️ newsletter roundup, including news, competitions and discounts: https://gcn.eu/3K7\n\nJoin us from 16-19 June 2022 in the stunning resort of Saalbach in the heart of the Austrian Alps for Global Bike Festival - the ultimate weekend of bikes, riding, music, entertainment and much, much more brought to you by GCN, GMBN and EMBN: https://gcn.eu/global-bike-festival\n\nVisit the GCN Shop - Shop Now: https://gcn.eu/6-Z\nSubscribe to GCN: http://gcn.eu/SubscribeToGCN\nRegister your interest in the GCN Club: https://www.gcnclub.com/\n#Cycling #GCN #RoadBike \n\nIf you enjoyed this video, make sure to give it a thumbs up and share it with your friends. 👍\n\nWatch more on GCN...\n📹  Conquering The World's Hardest Sportive! 👉 https://gcn.eu/OllieTDS\n\nMusic - licensed by Epidemic Sound:\n2d - Nylonia\nA Little Deja Vu (Instrumental Version) - Staffan Carlen\nBelow Horizon - Luwaks\nBug - Czar Donic\nCastles in the Sky - Across The Great Valley\nChanging Tides - Daniel Kaede\nCity of Thessaloniki - Trabant 33\nCurlicue - Jobii\nFantasy Parade (Instrumental Version) - Torii Wolf\nHeavy Words We're Holding - Trevor Kowalski\nMark My Words - Pearce Roswell\nNauseated - Pip Mondy\nOstersjon - Ooyy\nParadisio - Sum Wave\nReversed Beginning - Luwaks\nTelephone (Instrumental Version) - Blood Red Sun\nThe Cynic - At The End Of Times, Nothing\nThis Was Your Dream - Nylonia\nYou Know What I Want (Instrumental Version) - Staffan Carlen\n\nPhotos: © Velo Collection (TDW) / Getty Images & © Bettiniphoto / http://www.bettiniphoto.net/\n\nThe Global Cycling Network (GCN) is the largest and fastest-growing online cycling channel in the world, bringing together a global community of road cyclists to celebrate everything that’s great about the world of cycling. \n\nOur videos bring fans compelling daily content including expert tutorials, techniques, training, racing, cutting-edge bike tech, unparalleled behind the scenes event coverage, humour,  entertainment, and more. \n\nPresented by ex-pro riders, GCN offers a uniquely qualified insight into the world of cycling, and most importantly it’s fuelled by our passionate and enthusiastic fans – everyone who makes up the GCN community. We also bring you the latest and greatest tech to your attention, showcase the best places in the world to ride and get exclusive access to events and races. \n\nWelcome to the Global Cycling Network | Inside #cycling\n\nThanks to our sponsors:\n\nCastelli Clothing: https://gcn.eu/Castelli\nGiro Helmets: https://gcn.eu/Giro\nPinarello Bikes: https://gcn.eu/Pinarello\nZipp Wheels: https://gcn.eu/Zipp\nEnervit Nutrition: https://gcn.eu/Enervit\nTopeak Tools: http://gcn.eu/Topeak\nCanyon Bikes: http://gcn.eu/-Canyon\nPirelli Tyres: https://gcn.eu/Pirelli\nOrbea Bikes: http://gcn.eu/Orbea\nVision Wheels: http://gcn.eu/Vision\nWahoo Fitness: http://gcn.eu/Wahoo-Fitness \nPark Tool: http://gcn.eu/-parktool\nElite Bottles: https://gcn.eu/EliteBottles\nWhoop Fitness: https://gcn.eu/Whoop\nKomoot: https://gcn.eu/komoot\nSelle Italia: https://gcn.eu/SelleItalia\nZwift: https://gcn.eu/Zwift\nShimano Wheels: https://gcn.eu/Shimano\nShadow Stand: https://gcn.eu/ShadowStand\nDMT Shoes: https://gcn.eu/DMT\nMuc-Off: https://gcn.eu/MucOff\n\nFacebook: http://gcn.eu/gcnFb\nInstagram: http://gcn.eu/GCNInsta\nTwitter: http://gcn.eu/gcnTW\nYouTube Channel: http://gcn.eu/gcnYT\nThe GCN Club: http://gcn.eu/club\n\nGCN Japan: https://gcn.eu/subscribe-gcn-japan\nGCN Italia: https://gcn.eu/GCN-Italia\nGCN en Español: http://gcn.eu/Suscribirse\nGCN auf Deutsch: https://gcn.eu/auf-deutsch\nGCN en Français: https://gcn.eu/GCNENFRANCAIS\nGCN Tech: http://gcntech.co/subscribe\nGCN Training: https://gcn.eu/gcntraining\nGCN Racing: https://gcn.eu/gcn-racing\nGMBN: http://gmbn.eu/subscribe\nGMBN Tech: http://gmbn.tech/subscribe\nEMBN: http://embn.me/subscribe\n\nLeave us a comment below!",
    "publishDate": "2022-02-20T10:00:32.000Z",
    "title": "Can We Ride The World's Longest Pro Bike Race Route? | GCN vs Milan–San Remo",
    "urlTitle": "can-we-ride-the-worlds-longest-pro-bike-race-route-gcn-vs-milan-san-remo"
  },
  {
    "playlists": [],
    "topics": [],
    "public": true,
    "_id": "e183qY-wU4A",
    "__v": 0,
    "description": "With the UAE Tour being the first World Tour Race of the year, a lot of teams bring a raft of new tech to help them win! Alex looks around the mechanic's trucks to find nuggets of hot tech!\n\nIn association with the UAE Tour: www.theuaetour.com\n____________________\n🚴 With the 2022 road season promising to be one of the most exciting in recent memory, subscribe to GCN+ for live racing all year round, exclusive shows & cycling adventure films: https://gcn.eu/plus\nDownload the GCN App 📲  for FREE & be part of the world's largest cycling community: https://gcn.eu/app\nJoin thousands of other cycling fans in receiving our free weekly ✉️ newsletter roundup, including news, competitions and discounts: https://gcn.eu/3K7\n\nJoin us from 16-19 June 2022 in the stunning resort of Saalbach in the heart of the Austrian Alps for Global Bike Festival - the ultimate weekend of bikes, riding, music, entertainment and much, much more brought to you by GCN, GMBN and EMBN: https://gcn.eu/global-bike-festival\n\nSubscribe: http://gcntech.co/subscribetogcntech\nThe GCN Shop: https://gcn.eu/NewArrivals\n#Cycling #GCN #GCNTech #RoadBike\n\nWhich race's hot tech would you like to see next? Let us know in the comments below! \n\nIf you enjoyed this video, make sure to give it a thumbs up and share it with your friends. 👍\n\nWatch more on GCN Tech...\n📹 https://gcn.eu/6-W\n\nMusic - licensed by Epidemic Sound:\nUp in Smoke - Duke Herrington\nSlippin' Away - El Flaco Collective (1)\nDisco in the Jungle - Daniel Fridell\nLucky Shot - El Flaco Collective\n\nPhotos: © Velo Collection (TDW) / Getty Images & © Bettiniphoto / http://www.bettiniphoto.net/\n\nBrought to you by the world’s biggest cycling channel, the Global Cycling Network (GCN), GCN Tech is the only channel you need for all things bike tech – past, present and future.\n\nSimply put, we’re obsessed with tech: we seek out and showcase the best in bikes, components, tech, accessories, upgrades and more from races and events, tech shows and product launches across the globe to bring you the best in road bike technology.\n\nWe’ve also got great maintenance videos to help you get the most from your bike; pro-bike tours from all the biggest races; special features and the weekly GCN Tech Show. We also take a deeper look into the future of cycling, apps, smart tech and virtual riding. \n\nJoin us on the channel and the GCN App to submit your content, vote on the latest tech and keep abreast of exciting new trends. \n\nThanks to our sponsors:\n\nCastelli Clothing: https://gcn.eu/Castelli\nGiro Helmets: https://gcn.eu/Giro\nPinarello Bikes: https://gcn.eu/Pinarello\nZipp Wheels: https://gcn.eu/Zipp\nEnervit Nutrition: https://gcn.eu/Enervit\nTopeak Tools: http://gcn.eu/Topeak\nCanyon Bikes: http://gcn.eu/-Canyon\nPirelli Tyres: https://gcn.eu/Pirelli\nOrbea Bikes: http://gcn.eu/Orbea\nVision Wheels: http://gcn.eu/Vision\nWahoo Fitness: http://gcn.eu/Wahoo-Fitness \nPark Tool: http://gcn.eu/-parktool\nElite Bottles: https://gcn.eu/EliteBottles\nWhoop Fitness: https://gcn.eu/Whoop\nKomoot: https://gcn.eu/komoot\nSelle Italia: https://gcn.eu/SelleItalia\nZwift: https://gcn.eu/Zwift\nShimano Wheels: https://gcn.eu/Shimano\nShadow Stand: https://gcn.eu/ShadowStand\nDMT Shoes: https://gcn.eu/DMT\nMuc-Off: https://gcn.eu/MucOff\n\nFacebook: http://gcntech.co/gcntechfb\nInstagram: http://gcntech.co/gcntechinsta\nTwitter: http://gcntech.co/gcntechtweet\nYouTube: http://gcntech.co/subscribe\n\nGCN: http://gcn.eu/SubscribeToGCN\nGCN Japan: https://gcn.eu/subscribe-gcn-japan\nGCN Italia: https://gcn.eu/GCN-Italia\nGCN en Español: http://gcn.eu/Suscribirse\nGCN auf Deutsch: https://gcn.eu/auf-deutsch\nGCN en Français: https://gcn.eu/GCNENFRANCAIS\nGCN Training: https://gcn.eu/gcntraining\nGCN Racing: https://gcn.eu/gcn-racing\nGMBN: http://gmbn.eu/subscribe\nGMBN Tech: http://gmbn.tech/subscribe\nEMBN: http://embn.me/subscribe\n\nLeave us a comment below!",
    "publishDate": "2022-02-19T10:00:35.000Z",
    "title": "Hot Bike Tech From The UAE Tour!",
    "urlTitle": "hot-bike-tech-from-the-uae-tour"
  },
  {
    "playlists": [],
    "topics": [],
    "public": true,
    "_id": "S8B-rqqHIEg",
    "__v": 0,
    "description": "A debate that divides cyclists like no other, CX bike or gravel bikes, is there even a difference? Both have evolved to suit the needs of any cyclist off-road, but are they just the same thing? Si is here to check both out! Plus really want to know what YOU think, let us know!\n\nIn association with Trek 👉 https://gcn.eu/TrekBikes\n\nBig thanks to ShamXross for letting us use the cyclocross course which is on private land. Please, if you recognise the location, don't ride it! You'll have to wait until the next race so you don't risk putting the future of the course in jeopardy. Thanks. \n____________________\n🚴 With the 2022 road season promising to be one of the most exciting in recent memory, subscribe to GCN+ for live racing all year round, exclusive shows & cycling adventure films: https://gcn.eu/plus\nDownload the GCN App 📲  for FREE & be part of the world's largest cycling community: https://gcn.eu/app\nJoin thousands of other cycling fans in receiving our free weekly ✉️ newsletter roundup, including news, competitions and discounts: https://gcn.eu/3K7\n\nJoin us from 16-19 June 2022 in the stunning resort of Saalbach in the heart of the Austrian Alps for Global Bike Festival - the ultimate weekend of bikes, riding, music, entertainment and much, much more brought to you by GCN, GMBN and EMBN: https://gcn.eu/global-bike-festival\n\nVisit the GCN Shop - Shop Now: https://gcn.eu/6-V\nSubscribe to GCN: http://gcn.eu/SubscribeToGCN\nRegister your interest in the GCN Club: https://www.gcnclub.com/\n#Cycling #GCN #RoadBike \n\nIf you enjoyed this video, make sure to give it a thumbs up and share it with your friends. 👍\n\nWatch more on GCN...\n📹  What's It Like To Ride A Pro Gravel Race? 👉 https://gcn.eu/ManonFirstGravel\n\nMusic - licensed by Epidemic Sound:\nTriadox - Beautiful Minds \nSweet Sugar - OTE\nThe Murdered Dancer - Luella Gren\nThe Way Used to Be - Brendon Moeller\nTop Funnel - Ooyy\nPE Crescendo 8 - SFX Producer\nRecord Scratch 4 - SFX Producer\nSnow and All That - Ava Low\nLost in Atlantis - Smartface\nMarauder - Tigerblood Jewel\nPaid Marketing - Ooyy\nHacienda - Jett Everill\nHarp Ascend 2 - SFX Producer\nLFE Drone 5 - SFX Producer\nGlass Slide - SFX Producer\nGranny's Basement - Stationary Sign\nFifth Wall - Robert Ruth\nFilm Camera35mm 4 - SFX Producer\nDV Camera Open Tape - SFX Producer\nDancing in Your Head - Ava Low\nDifferent Times - Jett Everill\nCrescendo Whoosh 2 - SFX Producer\nCrescendo Whoosh 1 - SFX Producer\nCrescendo Ramp 2 - SFX Producer\nCrescendo Ramp 1 - SFX Producer\nCatching the Breeze - Chris Shards\nBy the Neon Sign - OTE\n\nPhotos: © Velo Collection (TDW) / Getty Images & © Bettiniphoto / http://www.bettiniphoto.net/\n\nThe Global Cycling Network (GCN) is the largest and fastest-growing online cycling channel in the world, bringing together a global community of road cyclists to celebrate everything that’s great about the world of cycling. \n\nOur videos bring fans compelling daily content including expert tutorials, techniques, training, racing, cutting-edge bike tech, unparalleled behind the scenes event coverage, humour,  entertainment, and more. \n\nPresented by ex-pro riders, GCN offers a uniquely qualified insight into the world of cycling, and most importantly it’s fuelled by our passionate and enthusiastic fans – everyone who makes up the GCN community. We also bring you the latest and greatest tech to your attention, showcase the best places in the world to ride and get exclusive access to events and races. \n\nWelcome to the Global Cycling Network | Inside #cycling\n\nThanks to our sponsors:\n\nCastelli Clothing: https://gcn.eu/Castelli\nGiro Helmets: https://gcn.eu/Giro\nPinarello Bikes: https://gcn.eu/Pinarello\nZipp Wheels: https://gcn.eu/Zipp\nEnervit Nutrition: https://gcn.eu/Enervit\nTopeak Tools: http://gcn.eu/Topeak\nCanyon Bikes: http://gcn.eu/-Canyon\nPirelli Tyres: https://gcn.eu/Pirelli\nOrbea Bikes: http://gcn.eu/Orbea\nVision Wheels: http://gcn.eu/Vision\nWahoo Fitness: http://gcn.eu/Wahoo-Fitness \nPark Tool: http://gcn.eu/-parktool\nElite Bottles: https://gcn.eu/EliteBottles\nWhoop Fitness: https://gcn.eu/Whoop\nKomoot: https://gcn.eu/komoot\nSelle Italia: https://gcn.eu/SelleItalia\nZwift: https://gcn.eu/Zwift\nShimano Wheels: https://gcn.eu/Shimano\nShadow Stand: https://gcn.eu/ShadowStand\nDMT Shoes: https://gcn.eu/DMT\nMuc-Off: https://gcn.eu/MucOff\n\nFacebook: http://gcn.eu/gcnFb\nInstagram: http://gcn.eu/GCNInsta\nTwitter: http://gcn.eu/gcnTW\nYouTube Channel: http://gcn.eu/gcnYT\nThe GCN Club: http://gcn.eu/club\n\nGCN Japan: https://gcn.eu/subscribe-gcn-japan\nGCN Italia: https://gcn.eu/GCN-Italia\nGCN en Español: http://gcn.eu/Suscribirse\nGCN auf Deutsch: https://gcn.eu/auf-deutsch\nGCN en Français: https://gcn.eu/GCNENFRANCAIS\nGCN Tech: http://gcntech.co/subscribe\nGCN Training: https://gcn.eu/gcntraining\nGCN Racing: https://gcn.eu/gcn-racing\nGMBN: http://gmbn.eu/subscribe\nGMBN Tech: http://gmbn.tech/subscribe\nEMBN: http://embn.me/subscribe\n\nLeave us a comment below!",
    "publishDate": "2022-02-19T10:00:25.000Z",
    "title": "Cyclo-Cross Vs Gravel: Same Bike, Different Name?",
    "urlTitle": "cyclo-cross-vs-gravel-same-bike-different-name"
  },
  {
    "playlists": [],
    "topics": [],
    "public": true,
    "_id": "T3D73eCOKVc",
    "__v": 0,
    "description": "400 miles, or around 640 kilometres is a really, REALLY long bicycle race. Si recently took part in his maiden Ultra Race, and learnt a few things about taking part in them - things he wished he knew when he was racing!\n____________________\n🚴 With the 2022 road season promising to be one of the most exciting in recent memory, subscribe to GCN+ for live racing all year round, exclusive shows & cycling adventure films: https://gcn.eu/plus\nDownload the GCN App 📲  for FREE & be part of the world's largest cycling community: https://gcn.eu/app\nJoin thousands of other cycling fans in receiving our free weekly ✉️ newsletter roundup, including news, competitions and discounts: https://gcn.eu/3K7\n\nJoin us from 16-19 June 2022 in the stunning resort of Saalbach in the heart of the Austrian Alps for Global Bike Festival - the ultimate weekend of bikes, riding, music, entertainment and much, much more brought to you by GCN, GMBN and EMBN: https://gcn.eu/global-bike-festival\n\nVisit the GCN Shop - Shop Now: https://gcn.eu/NewArrivals\nSubscribe to GCN: http://gcn.eu/SubscribeToGCN\nRegister your interest in the GCN Club: https://www.gcnclub.com/\n#Cycling #GCN #RoadBike \n\nWould you take part in an Ultra Race? Let us know in the comments! 👇\n\nIf you enjoyed this video, make sure to give it a thumbs up and share it with your friends. 👍\n\nTime Stamps: \n00:00 - Intro\n00:55 - It's Fun!\n01:46 - Nutrition \n03:30 - Luxuries/Creature Comforts \n05:10 - Pain!\n06:08 - Look After Yourself \n06:55 - Bring Chain Lube \n07:25 - Preparation Is Key!\n08:34 - Recovery\n\nWatch more on GCN...\n📹 Can Si Survive A 400 Mile Ultra Race? 👉 https://gcn.eu/6-T\n\nMusic - licensed by Epidemic Sound:\nEntrace - Jones Meadow\n\nPhotos: © Velo Collection (TDW) / Getty Images & © Bettiniphoto / http://www.bettiniphoto.net/\n\nThe Global Cycling Network (GCN) is the largest and fastest-growing online cycling channel in the world, bringing together a global community of road cyclists to celebrate everything that’s great about the world of cycling. \n\nOur videos bring fans compelling daily content including expert tutorials, techniques, training, racing, cutting-edge bike tech, unparalleled behind the scenes event coverage, humour,  entertainment, and more. \n\nPresented by ex-pro riders, GCN offers a uniquely qualified insight into the world of cycling, and most importantly it’s fuelled by our passionate and enthusiastic fans – everyone who makes up the GCN community. We also bring you the latest and greatest tech to your attention, showcase the best places in the world to ride and get exclusive access to events and races. \n\nWelcome to the Global Cycling Network | Inside #cycling\n\nThanks to our sponsors:\n\nCastelli Clothing: https://gcn.eu/Castelli\nGiro Helmets: https://gcn.eu/Giro\nPinarello Bikes: https://gcn.eu/Pinarello\nZipp Wheels: https://gcn.eu/Zipp\nEnervit Nutrition: https://gcn.eu/Enervit\nTopeak Tools: http://gcn.eu/Topeak\nCanyon Bikes: http://gcn.eu/-Canyon\nPirelli Tyres: https://gcn.eu/Pirelli\nOrbea Bikes: http://gcn.eu/Orbea\nVision Wheels: http://gcn.eu/Vision\nWahoo Fitness: http://gcn.eu/Wahoo-Fitness \nPark Tool: http://gcn.eu/-parktool\nElite Bottles: https://gcn.eu/EliteBottles\nWhoop Fitness: https://gcn.eu/Whoop\nKomoot: https://gcn.eu/komoot\nSelle Italia: https://gcn.eu/SelleItalia\nZwift: https://gcn.eu/Zwift\nShimano Wheels: https://gcn.eu/Shimano\nShadow Stand: https://gcn.eu/ShadowStand\nDMT Shoes: https://gcn.eu/DMT\nMuc-Off: https://gcn.eu/MucOff\n\nFacebook: http://gcn.eu/gcnFb\nInstagram: http://gcn.eu/GCNInsta\nTwitter: http://gcn.eu/gcnTW\nYouTube Channel: http://gcn.eu/gcnYT\nThe GCN Club: http://gcn.eu/club\n\nGCN Japan: https://gcn.eu/subscribe-gcn-japan\nGCN Italia: https://gcn.eu/GCN-Italia\nGCN en Español: http://gcn.eu/Suscribirse\nGCN auf Deutsch: https://gcn.eu/auf-deutsch\nGCN en Français: https://gcn.eu/GCNENFRANCAIS\nGCN Tech: http://gcntech.co/subscribe\nGCN Training: https://gcn.eu/gcntraining\nGCN Racing: https://gcn.eu/gcn-racing\nGMBN: http://gmbn.eu/subscribe\nGMBN Tech: http://gmbn.tech/subscribe\nEMBN: http://embn.me/subscribe\n\nLeave us a comment below!",
    "publishDate": "2022-02-18T15:33:42.000Z",
    "title": "8 Things I Learnt From Racing 400 Miles!",
    "urlTitle": "8-things-i-learnt-from-racing-400-miles"
  },
  {
    "playlists": [],
    "topics": [],
    "public": true,
    "_id": "wkY-sVss6c0",
    "__v": 0,
    "description": "Ever wondered how an ultrasonic chain cleaner works? Alex finds out!\n____________________\n🚴 With the 2022 road season promising to be one of the most exciting in recent memory, subscribe to GCN+ for live racing all year round, exclusive shows & cycling adventure films: https://gcn.eu/plus\nDownload the GCN App 📲  for FREE & be part of the world's largest cycling community: https://gcn.eu/app\nJoin thousands of other cycling fans in receiving our free weekly ✉️ newsletter roundup, including news, competitions and discounts: https://gcn.eu/3K7\n\nJoin us from 16-19 June 2022 in the stunning resort of Saalbach in the heart of the Austrian Alps for Global Bike Festival - the ultimate weekend of bikes, riding, music, entertainment and much, much more brought to you by GCN, GMBN and EMBN: https://gcn.eu/global-bike-festival\n\nSubscribe: http://gcntech.co/subscribetogcntech\nThe GCN Shop: https://gcn.eu/NewArrivals\n#Cycling #GCN #GCNTech #RoadBike\n\nIf you enjoyed this video, make sure to give it a thumbs up and share it with your friends. 👍\n\nMusic - licensed by Epidemic Sound\n\nPhotos: © Velo Collection (TDW) / Getty Images & © Bettiniphoto / http://www.bettiniphoto.net/\n\nBrought to you by the world’s biggest cycling channel, the Global Cycling Network (GCN), GCN Tech is the only channel you need for all things bike tech – past, present and future.\n\nSimply put, we’re obsessed with tech: we seek out and showcase the best in bikes, components, tech, accessories, upgrades and more from races and events, tech shows and product launches across the globe to bring you the best in road bike technology.\n\nWe’ve also got great maintenance videos to help you get the most from your bike; pro-bike tours from all the biggest races; special features and the weekly GCN Tech Show. We also take a deeper look into the future of cycling, apps, smart tech and virtual riding. \n\nJoin us on the channel and the GCN App to submit your content, vote on the latest tech and keep abreast of exciting new trends. \n\nThanks to our sponsors:\n\nCastelli Clothing: https://gcn.eu/Castelli\nGiro Helmets: https://gcn.eu/Giro\nPinarello Bikes: https://gcn.eu/Pinarello\nZipp Wheels: https://gcn.eu/Zipp\nEnervit Nutrition: https://gcn.eu/Enervit\nTopeak Tools: http://gcn.eu/Topeak\nCanyon Bikes: http://gcn.eu/-Canyon\nPirelli Tyres: https://gcn.eu/Pirelli\nOrbea Bikes: http://gcn.eu/Orbea\nVision Wheels: http://gcn.eu/Vision\nWahoo Fitness: http://gcn.eu/Wahoo-Fitness \nPark Tool: http://gcn.eu/-parktool\nElite Bottles: https://gcn.eu/EliteBottles\nWhoop Fitness: https://gcn.eu/Whoop\nKomoot: https://gcn.eu/komoot\nSelle Italia: https://gcn.eu/SelleItalia\nZwift: https://gcn.eu/Zwift\nShimano Wheels: https://gcn.eu/Shimano\nShadow Stand: https://gcn.eu/ShadowStand\nDMT Shoes: https://gcn.eu/DMT\nMuc-Off: https://gcn.eu/MucOff\n\nFacebook: http://gcntech.co/gcntechfb\nInstagram: http://gcntech.co/gcntechinsta\nTwitter: http://gcntech.co/gcntechtweet\nYouTube: http://gcntech.co/subscribe\n\nGCN: http://gcn.eu/SubscribeToGCN\nGCN Japan: https://gcn.eu/subscribe-gcn-japan\nGCN Italia: https://gcn.eu/GCN-Italia\nGCN en Español: http://gcn.eu/Suscribirse\nGCN auf Deutsch: https://gcn.eu/auf-deutsch\nGCN en Français: https://gcn.eu/GCNENFRANCAIS\nGCN Training: https://gcn.eu/gcntraining\nGCN Racing: https://gcn.eu/gcn-racing\nGMBN: http://gmbn.eu/subscribe\nGMBN Tech: http://gmbn.tech/subscribe\nEMBN: http://embn.me/subscribe\n\nLeave us a comment below!",
    "publishDate": "2022-02-18T14:00:35.000Z",
    "title": "How Do Ultrasonic Cleaners Work? #shorts",
    "urlTitle": "how-do-ultrasonic-cleaners-work-shorts"
  },
  {
    "playlists": [],
    "topics": [],
    "public": true,
    "_id": "_LOqP1lDdxA",
    "__v": 0,
    "description": "Manon attempts to break the individual pursuit record on an ebike!\n____________________\n🚴 With the 2022 road season promising to be one of the most exciting in recent memory, subscribe to GCN+ for live racing all year round, exclusive shows & cycling adventure films: https://gcn.eu/plus\nDownload the GCN App 📲  for FREE & be part of the world's largest cycling community: https://gcn.eu/app\nJoin thousands of other cycling fans in receiving our free weekly ✉️ newsletter roundup, including news, competitions and discounts: https://gcn.eu/3K7\n\nJoin us from 16-19 June 2022 in the stunning resort of Saalbach in the heart of the Austrian Alps for Global Bike Festival - the ultimate weekend of bikes, riding, music, entertainment and much, much more brought to you by GCN, GMBN and EMBN: https://gcn.eu/global-bike-festival\n\nVisit the GCN Shop - Shop Now: https://gcn.eu/NewArrivals\nSubscribe to GCN: http://gcn.eu/SubscribeToGCN\nRegister your interest in the GCN Club: https://www.gcnclub.com/\n#Cycling #GCN #RoadBike \n\nIf you enjoyed this video, make sure to give it a thumbs up and share it with your friends. 👍\n\nMusic - licensed by Epidemic Sound\n\nPhotos: © Velo Collection (TDW) / Getty Images & © Bettiniphoto / http://www.bettiniphoto.net/\n\nThe Global Cycling Network (GCN) is the largest and fastest-growing online cycling channel in the world, bringing together a global community of road cyclists to celebrate everything that’s great about the world of cycling. \n\nOur videos bring fans compelling daily content including expert tutorials, techniques, training, racing, cutting-edge bike tech, unparalleled behind the scenes event coverage, humour,  entertainment, and more. \n\nPresented by ex-pro riders, GCN offers a uniquely qualified insight into the world of cycling, and most importantly it’s fuelled by our passionate and enthusiastic fans – everyone who makes up the GCN community. We also bring you the latest and greatest tech to your attention, showcase the best places in the world to ride and get exclusive access to events and races. \n\nWelcome to the Global Cycling Network | Inside #cycling\n\nThanks to our sponsors:\n\nCastelli Clothing: https://gcn.eu/Castelli\nGiro Helmets: https://gcn.eu/Giro\nPinarello Bikes: https://gcn.eu/Pinarello\nZipp Wheels: https://gcn.eu/Zipp\nEnervit Nutrition: https://gcn.eu/Enervit\nTopeak Tools: http://gcn.eu/Topeak\nCanyon Bikes: http://gcn.eu/-Canyon\nPirelli Tyres: https://gcn.eu/Pirelli\nOrbea Bikes: http://gcn.eu/Orbea\nVision Wheels: http://gcn.eu/Vision\nWahoo Fitness: http://gcn.eu/Wahoo-Fitness \nPark Tool: http://gcn.eu/-parktool\nElite Bottles: https://gcn.eu/EliteBottles\nWhoop Fitness: https://gcn.eu/Whoop\nKomoot: https://gcn.eu/komoot\nSelle Italia: https://gcn.eu/SelleItalia\nZwift: https://gcn.eu/Zwift\nShimano Wheels: https://gcn.eu/Shimano\nShadow Stand: https://gcn.eu/ShadowStand\nDMT Shoes: https://gcn.eu/DMT\nMuc-Off: https://gcn.eu/MucOff\n\nFacebook: http://gcn.eu/gcnFb\nInstagram: http://gcn.eu/GCNInsta\nTwitter: http://gcn.eu/gcnTW\nYouTube Channel: http://gcn.eu/gcnYT\nThe GCN Club: http://gcn.eu/club\n\nGCN Japan: https://gcn.eu/subscribe-gcn-japan\nGCN Italia: https://gcn.eu/GCN-Italia\nGCN en Español: http://gcn.eu/Suscribirse\nGCN auf Deutsch: https://gcn.eu/auf-deutsch\nGCN en Français: https://gcn.eu/GCNENFRANCAIS\nGCN Tech: http://gcntech.co/subscribe\nGCN Training: https://gcn.eu/gcntraining\nGCN Racing: https://gcn.eu/gcn-racing\nGMBN: http://gmbn.eu/subscribe\nGMBN Tech: http://gmbn.tech/subscribe\nEMBN: http://embn.me/subscribe\n\nLeave us a comment below!",
    "publishDate": "2022-02-18T14:00:13.000Z",
    "title": "Manon, Start Your Engine! #shorts",
    "urlTitle": "manon-start-your-engine-shorts"
  }
]
